{"trial_id": "04", "hyperparameters": {"space": [{"class_name": "Int", "config": {"name": "units_1", "default": null, "conditions": [], "min_value": 16, "max_value": 256, "step": 16, "sampling": "linear"}}, {"class_name": "Int", "config": {"name": "units_2", "default": null, "conditions": [], "min_value": 16, "max_value": 256, "step": 16, "sampling": "linear"}}, {"class_name": "Int", "config": {"name": "units_3", "default": null, "conditions": [], "min_value": 16, "max_value": 256, "step": 16, "sampling": "linear"}}, {"class_name": "Int", "config": {"name": "units_4", "default": null, "conditions": [], "min_value": 16, "max_value": 256, "step": 16, "sampling": "linear"}}, {"class_name": "Int", "config": {"name": "units_5", "default": null, "conditions": [], "min_value": 16, "max_value": 256, "step": 16, "sampling": "linear"}}, {"class_name": "Int", "config": {"name": "units_6", "default": null, "conditions": [], "min_value": 16, "max_value": 256, "step": 16, "sampling": "linear"}}, {"class_name": "Int", "config": {"name": "units_7", "default": null, "conditions": [], "min_value": 16, "max_value": 256, "step": 16, "sampling": "linear"}}, {"class_name": "Choice", "config": {"name": "dropout_1", "default": 0.0, "conditions": [], "values": [0.0, 0.2, 0.5, 0.8], "ordered": true}}, {"class_name": "Choice", "config": {"name": "dropout_2", "default": 0.0, "conditions": [], "values": [0.0, 0.2, 0.5, 0.8], "ordered": true}}, {"class_name": "Choice", "config": {"name": "dropout_3", "default": 0.0, "conditions": [], "values": [0.0, 0.2, 0.5, 0.8], "ordered": true}}, {"class_name": "Choice", "config": {"name": "ls", "default": 0.01, "conditions": [], "values": [0.01, 0.001, 1e-05], "ordered": true}}, {"class_name": "Choice", "config": {"name": "lr", "default": 0.01, "conditions": [], "values": [0.01, 0.001, 1e-05], "ordered": true}}], "values": {"units_1": 176, "units_2": 160, "units_3": 32, "units_4": 64, "units_5": 16, "units_6": 208, "units_7": 144, "dropout_1": 0.5, "dropout_2": 0.8, "dropout_3": 0.2, "ls": 1e-05, "lr": 0.01}}, "metrics": {"metrics": {"loss": {"direction": "min", "observations": [{"value": [0.720889538526535], "step": 1}]}, "AUC": {"direction": "max", "observations": [{"value": [0.4875921308994293], "step": 1}]}, "val_loss": {"direction": "min", "observations": [{"value": [0.6930921077728271], "step": 1}]}, "val_AUC": {"direction": "max", "observations": [{"value": [0.5051923096179962], "step": 1}]}}}, "score": 0.5051923096179962, "best_step": 1, "status": "COMPLETED", "message": null}